wave_solver/__init__.py
wave_solver/boundary_conditions.py
wave_solver/cli.py
wave_solver/initial_conditions.py
wave_solver/main.py
wave_solver/wave_solver.py
wave_solver_2d-0.2.0.dist-info/licenses/LICENSE
wave_solver_2d-0.2.0.dist-info/METADATA
wave_solver_2d-0.2.0.dist-info/WHEEL
wave_solver_2d-0.2.0.dist-info/entry_points.txt
wave_solver_2d-0.2.0.dist-info/top_level.txt
wave_solver_2d-0.2.0.dist-info/RECORD
